[{"line":1,"elements":[{"line":4,"name":"","description":"","type":"background","keyword":"Background","steps":[{"name":"url apiUrl","result":{"duration":76900,"status":"passed"},"match":{"location":"karate","arguments":[]},"keyword":"*","line":5,"doc_string":{"content_type":"","value":"09:52:43.210 karate.env system property was: uat","line":5}}]},{"line":18,"name":"Consultar uma restrição pelo CPF - Positivo","description":"","id":"consultar-uma-restrição-pelo-cpf---positivo","type":"scenario","keyword":"Scenario Outline","steps":[{"name":"path \"\/restricoes\/97093236014\"","result":{"duration":4932500,"status":"passed"},"match":{"location":"karate","arguments":[]},"keyword":"Given","line":9},{"name":"method get","result":{"duration":217027500,"status":"passed"},"match":{"location":"karate","arguments":[]},"keyword":"When","line":10},{"name":"status 200","result":{"duration":48500,"status":"passed"},"match":{"location":"karate","arguments":[]},"keyword":"Then","line":11},{"name":"print response","result":{"duration":617300,"status":"passed"},"match":{"location":"karate","arguments":[]},"keyword":"And","line":12,"doc_string":{"content_type":"","value":"09:52:43.459 [print] {\n  \"mensagem\": \"O CPF 97093236014 tem problema\"\n}","line":12}},{"name":"match response.mensagem ==  \"O CPF 97093236014 tem problema\"","result":{"duration":9484500,"status":"passed"},"match":{"location":"karate","arguments":[]},"keyword":"And","line":13}]},{"line":4,"name":"","description":"","type":"background","keyword":"Background","steps":[{"name":"url apiUrl","result":{"duration":22800,"status":"passed"},"match":{"location":"karate","arguments":[]},"keyword":"*","line":5,"doc_string":{"content_type":"","value":"09:52:43.485 karate.env system property was: uat","line":5}}]},{"line":19,"name":"Consultar uma restrição pelo CPF - Positivo","description":"","id":"consultar-uma-restrição-pelo-cpf---positivo","type":"scenario","keyword":"Scenario Outline","steps":[{"name":"path \"\/restricoes\/60094146012\"","result":{"duration":2819200,"status":"passed"},"match":{"location":"karate","arguments":[]},"keyword":"Given","line":9},{"name":"method get","result":{"duration":16661100,"status":"passed"},"match":{"location":"karate","arguments":[]},"keyword":"When","line":10},{"name":"status 200","result":{"duration":15600,"status":"passed"},"match":{"location":"karate","arguments":[]},"keyword":"Then","line":11},{"name":"print response","result":{"duration":647200,"status":"passed"},"match":{"location":"karate","arguments":[]},"keyword":"And","line":12,"doc_string":{"content_type":"","value":"09:52:43.512 [print] {\n  \"mensagem\": \"O CPF 60094146012 tem problema\"\n}","line":12}},{"name":"match response.mensagem ==  \"O CPF 60094146012 tem problema\"","result":{"duration":8010300,"status":"passed"},"match":{"location":"karate","arguments":[]},"keyword":"And","line":13}]},{"line":4,"name":"","description":"","type":"background","keyword":"Background","steps":[{"name":"url apiUrl","result":{"duration":27200,"status":"passed"},"match":{"location":"karate","arguments":[]},"keyword":"*","line":5,"doc_string":{"content_type":"","value":"09:52:43.538 karate.env system property was: uat","line":5}}]},{"line":20,"name":"Consultar uma restrição pelo CPF - Positivo","description":"","id":"consultar-uma-restrição-pelo-cpf---positivo","type":"scenario","keyword":"Scenario Outline","steps":[{"name":"path \"\/restricoes\/84809766080\"","result":{"duration":4930100,"status":"passed"},"match":{"location":"karate","arguments":[]},"keyword":"Given","line":9},{"name":"method get","result":{"duration":14103900,"status":"passed"},"match":{"location":"karate","arguments":[]},"keyword":"When","line":10},{"name":"status 200","result":{"duration":11400,"status":"passed"},"match":{"location":"karate","arguments":[]},"keyword":"Then","line":11},{"name":"print response","result":{"duration":393500,"status":"passed"},"match":{"location":"karate","arguments":[]},"keyword":"And","line":12,"doc_string":{"content_type":"","value":"09:52:43.563 [print] {\n  \"mensagem\": \"O CPF 84809766080 tem problema\"\n}","line":12}},{"name":"match response.mensagem ==  \"O CPF 84809766080 tem problema\"","result":{"duration":3491600,"status":"passed"},"match":{"location":"karate","arguments":[]},"keyword":"And","line":13}]},{"line":4,"name":"","description":"","type":"background","keyword":"Background","steps":[{"name":"url apiUrl","result":{"duration":24300,"status":"passed"},"match":{"location":"karate","arguments":[]},"keyword":"*","line":5,"doc_string":{"content_type":"","value":"09:52:43.581 karate.env system property was: uat","line":5}}]},{"line":21,"name":"Consultar uma restrição pelo CPF - Positivo","description":"","id":"consultar-uma-restrição-pelo-cpf---positivo","type":"scenario","keyword":"Scenario Outline","steps":[{"name":"path \"\/restricoes\/62648716050\"","result":{"duration":2755400,"status":"passed"},"match":{"location":"karate","arguments":[]},"keyword":"Given","line":9},{"name":"method get","result":{"duration":13296200,"status":"passed"},"match":{"location":"karate","arguments":[]},"keyword":"When","line":10},{"name":"status 200","result":{"duration":10000,"status":"passed"},"match":{"location":"karate","arguments":[]},"keyword":"Then","line":11},{"name":"print response","result":{"duration":400800,"status":"passed"},"match":{"location":"karate","arguments":[]},"keyword":"And","line":12,"doc_string":{"content_type":"","value":"09:52:43.601 [print] {\n  \"mensagem\": \"O CPF 62648716050 tem problema\"\n}","line":12}},{"name":"match response.mensagem ==  \"O CPF 62648716050 tem problema\"","result":{"duration":3796900,"status":"passed"},"match":{"location":"karate","arguments":[]},"keyword":"And","line":13}]},{"line":4,"name":"","description":"","type":"background","keyword":"Background","steps":[{"name":"url apiUrl","result":{"duration":29400,"status":"passed"},"match":{"location":"karate","arguments":[]},"keyword":"*","line":5,"doc_string":{"content_type":"","value":"09:52:43.616 karate.env system property was: uat","line":5}}]},{"line":22,"name":"Consultar uma restrição pelo CPF - Positivo","description":"","id":"consultar-uma-restrição-pelo-cpf---positivo","type":"scenario","keyword":"Scenario Outline","steps":[{"name":"path \"\/restricoes\/26276298085\"","result":{"duration":4555500,"status":"passed"},"match":{"location":"karate","arguments":[]},"keyword":"Given","line":9},{"name":"method get","result":{"duration":14203300,"status":"passed"},"match":{"location":"karate","arguments":[]},"keyword":"When","line":10},{"name":"status 200","result":{"duration":71900,"status":"passed"},"match":{"location":"karate","arguments":[]},"keyword":"Then","line":11},{"name":"print response","result":{"duration":847200,"status":"passed"},"match":{"location":"karate","arguments":[]},"keyword":"And","line":12,"doc_string":{"content_type":"","value":"09:52:43.642 [print] {\n  \"mensagem\": \"O CPF 26276298085 tem problema\"\n}","line":12}},{"name":"match response.mensagem ==  \"O CPF 26276298085 tem problema\"","result":{"duration":3711700,"status":"passed"},"match":{"location":"karate","arguments":[]},"keyword":"And","line":13}]},{"line":4,"name":"","description":"","type":"background","keyword":"Background","steps":[{"name":"url apiUrl","result":{"duration":16200,"status":"passed"},"match":{"location":"karate","arguments":[]},"keyword":"*","line":5,"doc_string":{"content_type":"","value":"09:52:43.661 karate.env system property was: uat","line":5}}]},{"line":23,"name":"Consultar uma restrição pelo CPF - Positivo","description":"","id":"consultar-uma-restrição-pelo-cpf---positivo","type":"scenario","keyword":"Scenario Outline","steps":[{"name":"path \"\/restricoes\/01317496094\"","result":{"duration":2367600,"status":"passed"},"match":{"location":"karate","arguments":[]},"keyword":"Given","line":9},{"name":"method get","result":{"duration":14169100,"status":"passed"},"match":{"location":"karate","arguments":[]},"keyword":"When","line":10},{"name":"status 200","result":{"duration":11100,"status":"passed"},"match":{"location":"karate","arguments":[]},"keyword":"Then","line":11},{"name":"print response","result":{"duration":365600,"status":"passed"},"match":{"location":"karate","arguments":[]},"keyword":"And","line":12,"doc_string":{"content_type":"","value":"09:52:43.680 [print] {\n  \"mensagem\": \"O CPF 01317496094 tem problema\"\n}","line":12}},{"name":"match response.mensagem ==  \"O CPF 01317496094 tem problema\"","result":{"duration":2654700,"status":"passed"},"match":{"location":"karate","arguments":[]},"keyword":"And","line":13}]},{"line":4,"name":"","description":"","type":"background","keyword":"Background","steps":[{"name":"url apiUrl","result":{"duration":48200,"status":"passed"},"match":{"location":"karate","arguments":[]},"keyword":"*","line":5,"doc_string":{"content_type":"","value":"09:52:43.695 karate.env system property was: uat","line":5}}]},{"line":24,"name":"Consultar uma restrição pelo CPF - Positivo","description":"","id":"consultar-uma-restrição-pelo-cpf---positivo","type":"scenario","keyword":"Scenario Outline","steps":[{"name":"path \"\/restricoes\/55856777050\"","result":{"duration":4867100,"status":"passed"},"match":{"location":"karate","arguments":[]},"keyword":"Given","line":9},{"name":"method get","result":{"duration":16667100,"status":"passed"},"match":{"location":"karate","arguments":[]},"keyword":"When","line":10},{"name":"status 200","result":{"duration":62300,"status":"passed"},"match":{"location":"karate","arguments":[]},"keyword":"Then","line":11},{"name":"print response","result":{"duration":1202900,"status":"passed"},"match":{"location":"karate","arguments":[]},"keyword":"And","line":12,"doc_string":{"content_type":"","value":"09:52:43.724 [print] {\n  \"mensagem\": \"O CPF 55856777050 tem problema\"\n}","line":12}},{"name":"match response.mensagem ==  \"O CPF 55856777050 tem problema\"","result":{"duration":2917000,"status":"passed"},"match":{"location":"karate","arguments":[]},"keyword":"And","line":13}]},{"line":4,"name":"","description":"","type":"background","keyword":"Background","steps":[{"name":"url apiUrl","result":{"duration":20400,"status":"passed"},"match":{"location":"karate","arguments":[]},"keyword":"*","line":5,"doc_string":{"content_type":"","value":"09:52:43.741 karate.env system property was: uat","line":5}}]},{"line":25,"name":"Consultar uma restrição pelo CPF - Positivo","description":"","id":"consultar-uma-restrição-pelo-cpf---positivo","type":"scenario","keyword":"Scenario Outline","steps":[{"name":"path \"\/restricoes\/19626829001\"","result":{"duration":2719000,"status":"passed"},"match":{"location":"karate","arguments":[]},"keyword":"Given","line":9},{"name":"method get","result":{"duration":15960100,"status":"passed"},"match":{"location":"karate","arguments":[]},"keyword":"When","line":10},{"name":"status 200","result":{"duration":12700,"status":"passed"},"match":{"location":"karate","arguments":[]},"keyword":"Then","line":11},{"name":"print response","result":{"duration":398500,"status":"passed"},"match":{"location":"karate","arguments":[]},"keyword":"And","line":12,"doc_string":{"content_type":"","value":"09:52:43.766 [print] {\n  \"mensagem\": \"O CPF 19626829001 tem problema\"\n}","line":12}},{"name":"match response.mensagem ==  \"O CPF 19626829001 tem problema\"","result":{"duration":3596600,"status":"passed"},"match":{"location":"karate","arguments":[]},"keyword":"And","line":13}]},{"line":4,"name":"","description":"","type":"background","keyword":"Background","steps":[{"name":"url apiUrl","result":{"duration":15400,"status":"passed"},"match":{"location":"karate","arguments":[]},"keyword":"*","line":5,"doc_string":{"content_type":"","value":"09:52:43.783 karate.env system property was: uat","line":5}}]},{"line":26,"name":"Consultar uma restrição pelo CPF - Positivo","description":"","id":"consultar-uma-restrição-pelo-cpf---positivo","type":"scenario","keyword":"Scenario Outline","steps":[{"name":"path \"\/restricoes\/24094592008\"","result":{"duration":6552000,"status":"passed"},"match":{"location":"karate","arguments":[]},"keyword":"Given","line":9},{"name":"method get","result":{"duration":18734800,"status":"passed"},"match":{"location":"karate","arguments":[]},"keyword":"When","line":10},{"name":"status 200","result":{"duration":16600,"status":"passed"},"match":{"location":"karate","arguments":[]},"keyword":"Then","line":11},{"name":"print response","result":{"duration":601600,"status":"passed"},"match":{"location":"karate","arguments":[]},"keyword":"And","line":12,"doc_string":{"content_type":"","value":"09:52:43.812 [print] {\n  \"mensagem\": \"O CPF 24094592008 tem problema\"\n}","line":12}},{"name":"match response.mensagem ==  \"O CPF 24094592008 tem problema\"","result":{"duration":2783300,"status":"passed"},"match":{"location":"karate","arguments":[]},"keyword":"And","line":13}]},{"line":4,"name":"","description":"","type":"background","keyword":"Background","steps":[{"name":"url apiUrl","result":{"duration":14700,"status":"passed"},"match":{"location":"karate","arguments":[]},"keyword":"*","line":5,"doc_string":{"content_type":"","value":"09:52:43.827 karate.env system property was: uat","line":5}}]},{"line":27,"name":"Consultar uma restrição pelo CPF - Positivo","description":"","id":"consultar-uma-restrição-pelo-cpf---positivo","type":"scenario","keyword":"Scenario Outline","steps":[{"name":"path \"\/restricoes\/58063164083\"","result":{"duration":2076300,"status":"passed"},"match":{"location":"karate","arguments":[]},"keyword":"Given","line":9},{"name":"method get","result":{"duration":17906600,"status":"passed"},"match":{"location":"karate","arguments":[]},"keyword":"When","line":10},{"name":"status 200","result":{"duration":13400,"status":"passed"},"match":{"location":"karate","arguments":[]},"keyword":"Then","line":11},{"name":"print response","result":{"duration":511200,"status":"passed"},"match":{"location":"karate","arguments":[]},"keyword":"And","line":12,"doc_string":{"content_type":"","value":"09:52:43.850 [print] {\n  \"mensagem\": \"O CPF 58063164083 tem problema\"\n}","line":12}},{"name":"match response.mensagem ==  \"O CPF 58063164083 tem problema\"","result":{"duration":3133900,"status":"passed"},"match":{"location":"karate","arguments":[]},"keyword":"And","line":13}]},{"line":4,"name":"","description":"","type":"background","keyword":"Background","steps":[{"name":"url apiUrl","result":{"duration":17200,"status":"passed"},"match":{"location":"karate","arguments":[]},"keyword":"*","line":5,"doc_string":{"content_type":"","value":"09:52:43.865 karate.env system property was: uat","line":5}}]},{"line":40,"name":"Consultar uma restrição pelo CPF - Negativo","description":"","id":"consultar-uma-restrição-pelo-cpf---negativo","type":"scenario","keyword":"Scenario Outline","steps":[{"name":"path \"\/restricoes\/66156841873\"","result":{"duration":3588900,"status":"passed"},"match":{"location":"karate","arguments":[]},"keyword":"Given","line":32},{"name":"method get","result":{"duration":16775600,"status":"passed"},"match":{"location":"karate","arguments":[]},"keyword":"When","line":33},{"name":"status 204","result":{"duration":13100,"status":"passed"},"match":{"location":"karate","arguments":[]},"keyword":"Then","line":34},{"name":"print response","result":{"duration":848000,"status":"passed"},"match":{"location":"karate","arguments":[]},"keyword":"And","line":35,"doc_string":{"content_type":"","value":"09:52:43.890 [print]","line":35}},{"name":"match response ==  \"\"","result":{"duration":3218700,"status":"passed"},"match":{"location":"karate","arguments":[]},"keyword":"And","line":36}]},{"line":4,"name":"","description":"","type":"background","keyword":"Background","steps":[{"name":"url apiUrl","result":{"duration":19100,"status":"passed"},"match":{"location":"karate","arguments":[]},"keyword":"*","line":5,"doc_string":{"content_type":"","value":"09:52:43.906 karate.env system property was: uat","line":5}}]},{"line":41,"name":"Consultar uma restrição pelo CPF - Negativo","description":"","id":"consultar-uma-restrição-pelo-cpf---negativo","type":"scenario","keyword":"Scenario Outline","steps":[{"name":"path \"\/restricoes\/82921172534\"","result":{"duration":4697900,"status":"passed"},"match":{"location":"karate","arguments":[]},"keyword":"Given","line":32},{"name":"method get","result":{"duration":12701300,"status":"passed"},"match":{"location":"karate","arguments":[]},"keyword":"When","line":33},{"name":"status 204","result":{"duration":17100,"status":"passed"},"match":{"location":"karate","arguments":[]},"keyword":"Then","line":34},{"name":"print response","result":{"duration":780400,"status":"passed"},"match":{"location":"karate","arguments":[]},"keyword":"And","line":35,"doc_string":{"content_type":"","value":"09:52:43.927 [print]","line":35}},{"name":"match response ==  \"\"","result":{"duration":591700,"status":"passed"},"match":{"location":"karate","arguments":[]},"keyword":"And","line":36}]},{"line":4,"name":"","description":"","type":"background","keyword":"Background","steps":[{"name":"url apiUrl","result":{"duration":32200,"status":"passed"},"match":{"location":"karate","arguments":[]},"keyword":"*","line":5,"doc_string":{"content_type":"","value":"09:52:43.940 karate.env system property was: uat","line":5}}]},{"line":42,"name":"Consultar uma restrição pelo CPF - Negativo","description":"","id":"consultar-uma-restrição-pelo-cpf---negativo","type":"scenario","keyword":"Scenario Outline","steps":[{"name":"path \"\/restricoes\/08632382624\"","result":{"duration":3067800,"status":"passed"},"match":{"location":"karate","arguments":[]},"keyword":"Given","line":32},{"name":"method get","result":{"duration":13524100,"status":"passed"},"match":{"location":"karate","arguments":[]},"keyword":"When","line":33},{"name":"status 204","result":{"duration":38300,"status":"passed"},"match":{"location":"karate","arguments":[]},"keyword":"Then","line":34},{"name":"print response","result":{"duration":382700,"status":"passed"},"match":{"location":"karate","arguments":[]},"keyword":"And","line":35,"doc_string":{"content_type":"","value":"09:52:43.964 [print]","line":35}},{"name":"match response ==  \"\"","result":{"duration":287500,"status":"passed"},"match":{"location":"karate","arguments":[]},"keyword":"And","line":36}]},{"line":4,"name":"","description":"","type":"background","keyword":"Background","steps":[{"name":"url apiUrl","result":{"duration":18100,"status":"passed"},"match":{"location":"karate","arguments":[]},"keyword":"*","line":5,"doc_string":{"content_type":"","value":"09:52:43.976 karate.env system property was: uat","line":5}}]},{"line":43,"name":"Consultar uma restrição pelo CPF - Negativo","description":"","id":"consultar-uma-restrição-pelo-cpf---negativo","type":"scenario","keyword":"Scenario Outline","steps":[{"name":"path \"\/restricoes\/95653373842\"","result":{"duration":3044400,"status":"passed"},"match":{"location":"karate","arguments":[]},"keyword":"Given","line":32},{"name":"method get","result":{"duration":15863900,"status":"passed"},"match":{"location":"karate","arguments":[]},"keyword":"When","line":33},{"name":"status 204","result":{"duration":11700,"status":"passed"},"match":{"location":"karate","arguments":[]},"keyword":"Then","line":34},{"name":"print response","result":{"duration":315900,"status":"passed"},"match":{"location":"karate","arguments":[]},"keyword":"And","line":35,"doc_string":{"content_type":"","value":"09:52:43.999 [print]","line":35}},{"name":"match response ==  \"\"","result":{"duration":278000,"status":"passed"},"match":{"location":"karate","arguments":[]},"keyword":"And","line":36}]},{"line":4,"name":"","description":"","type":"background","keyword":"Background","steps":[{"name":"url apiUrl","result":{"duration":21700,"status":"passed"},"match":{"location":"karate","arguments":[]},"keyword":"*","line":5,"doc_string":{"content_type":"","value":"09:52:44.014 karate.env system property was: uat","line":5}}]},{"line":44,"name":"Consultar uma restrição pelo CPF - Negativo","description":"","id":"consultar-uma-restrição-pelo-cpf---negativo","type":"scenario","keyword":"Scenario Outline","steps":[{"name":"path \"\/restricoes\/22251237135\"","result":{"duration":4083900,"status":"passed"},"match":{"location":"karate","arguments":[]},"keyword":"Given","line":32},{"name":"method get","result":{"duration":14029100,"status":"passed"},"match":{"location":"karate","arguments":[]},"keyword":"When","line":33},{"name":"status 204","result":{"duration":83900,"status":"passed"},"match":{"location":"karate","arguments":[]},"keyword":"Then","line":34},{"name":"print response","result":{"duration":1220100,"status":"passed"},"match":{"location":"karate","arguments":[]},"keyword":"And","line":35,"doc_string":{"content_type":"","value":"09:52:44.037 [print]","line":35}},{"name":"match response ==  \"\"","result":{"duration":781600,"status":"passed"},"match":{"location":"karate","arguments":[]},"keyword":"And","line":36}]}],"name":"services\/features\/001_restricoes.feature","description":"CT 01 Consulta Restrições","id":"ct-01-consulta-restrições","keyword":"Feature","uri":"services\/features\/001_restricoes.feature"}]